akeneo_connector/__init__.py
akeneo_connector/akeneo_attribute.py
akeneo_connector/akeneo_connector.py
akeneo_connector/akeneo_paginator.py
akeneo_connector/akeneo_product.py
akeneo_connector/akeneo_units.py
akeneo_connector/decorators.py
akeneo_connector-0.1.49.dist-info/LICENSE
akeneo_connector-0.1.49.dist-info/METADATA
akeneo_connector-0.1.49.dist-info/WHEEL
akeneo_connector-0.1.49.dist-info/top_level.txt
akeneo_connector-0.1.49.dist-info/RECORD
