Metadata-Version: 2.1
Name: akeneo_connector
Version: 0.1.49
Summary: Akeneo Connector is a Python package that simplifies interacting with Akeneo's REST API. It provides classes for making HTTP requests to Akeneo endpoints, handling pagination in responses, and managing product data in Akeneo.
Home-page: https://github.com/bakeable/akeneo-connector
Author: Robin Bakker
Author-email: robin@bakeable.nl
License: MIT
Classifier: Programming Language :: Python :: 3
Classifier: License :: OSI Approved :: MIT License
Classifier: Operating System :: OS Independent
Requires-Python: >=3.12
License-File: LICENSE
Requires-Dist: requests >=2.31.0
Requires-Dist: python-dotenv >=1.0.1
